chaos_features/__init__.py
chaos_features/apps.py
chaos_features/models.py
chaos_features/urls.py
chaos_features/views.py
chaos_features/static/css/chaos_features.css
chaos_features/static/js/chaos_features.js
chaos_features/templates/chaos_features/base.html
django_chaos_features-0.1.0.dist-info/DESCRIPTION.rst
django_chaos_features-0.1.0.dist-info/METADATA
django_chaos_features-0.1.0.dist-info/RECORD
django_chaos_features-0.1.0.dist-info/WHEEL
django_chaos_features-0.1.0.dist-info/metadata.json
django_chaos_features-0.1.0.dist-info/top_level.txt
