Metadata-Version: 2.0
Name: django-chaos-features
Version: 0.1.0
Summary: Features
Home-page: https://github.com/george-silva/django-chaos-features
Author: George Silva
Author-email: georger.silva@gmail.com
License: MIT
Keywords: django-chaos-features
Platform: UNKNOWN
Classifier: Development Status :: 3 - Alpha
Classifier: Framework :: Django :: 1.11
Classifier: Framework :: Django :: 2.0
Classifier: Intended Audience :: Developers
Classifier: License :: OSI Approved :: BSD License
Classifier: Natural Language :: English
Classifier: Programming Language :: Python :: 2
Classifier: Programming Language :: Python :: 2.7
Classifier: Programming Language :: Python :: 3
Classifier: Programming Language :: Python :: 3.4
Classifier: Programming Language :: Python :: 3.5
Classifier: Programming Language :: Python :: 3.6
